darwinpyspark/__init__.py
darwinpyspark/darwinpyspark.py
darwinpyspark-0.0.2.dist-info/LICENSE
darwinpyspark-0.0.2.dist-info/METADATA
darwinpyspark-0.0.2.dist-info/WHEEL
darwinpyspark-0.0.2.dist-info/top_level.txt
darwinpyspark-0.0.2.dist-info/RECORD
