Metadata-Version: 2.1
Name: darwinpyspark
Version: 0.0.2
Summary: A package for interacting with the V7 platform via Pyspark
Home-page: https://github.com/v7labs/darwinpyspark
Author: Harry Hands
Author-email: harry.hands@v7labs.com
License: UNKNOWN
Platform: UNKNOWN
Classifier: License :: OSI Approved :: MIT License
License-File: LICENSE
Requires-Dist: requests
